{"_type": "News", "readLink": "https://api.cognitive.microsoft.com/api/v7/news/search?q=%22Scott+Dunham%22%2b%22San+Jose%22", "queryContext": {"originalQuery": "\"Scott Dunham\"+\"San Jose\"", "adultIntent": false}, "totalEstimatedMatches": 1, "sort": [{"name": "Best match", "id": "relevance", "isSelected": true, "url": "https://api.cognitive.microsoft.com/api/v7/news/search?q=%22Scott+Dunham%22%2b%22San+Jose%22"}, {"name": "Most recent", "id": "date", "isSelected": false, "url": "https://api.cognitive.microsoft.com/api/v7/news/search?q=%22Scott+Dunham%22%2b%22San+Jose%22&sortby=date"}], "value": [{"name": "<b>Scott Dunham</b>", "url": "https://sanfrancisco.cbslocal.com/tag/scott-dunham/", "description": "<b>San Jose</b> Police Officer&#39;s Pinpoint Shot Killed Man Who Gunned Down Fellow OfficerThe man who shot dead a <b>San Jose</b> police officer was then shot by a fellow lawman in a pinpoint shot that killed him ...", "provider": [{"_type": "Organization", "name": "CBS SF BayArea"}], "datePublished": "2015-03-25T06:51:00.0000000Z"}]}