{"_type": "News", "readLink": "https://api.cognitive.microsoft.com/api/v7/news/search?q=%22David+Parker%22%2b%22Mansfield%22", "queryContext": {"originalQuery": "\"David Parker\"+\"Mansfield\"", "adultIntent": false}, "totalEstimatedMatches": 1, "sort": [{"name": "Best match", "id": "relevance", "isSelected": true, "url": "https://api.cognitive.microsoft.com/api/v7/news/search?q=%22David+Parker%22%2b%22Mansfield%22"}, {"name": "Most recent", "id": "date", "isSelected": false, "url": "https://api.cognitive.microsoft.com/api/v7/news/search?q=%22David+Parker%22%2b%22Mansfield%22&sortby=date"}], "value": [{"name": "Millersville University Spring 2020 Graduates", "url": "https://lancasteronline.com/news/community/millersville-university-spring-2020-graduates/article_ceb258d2-bc05-11ea-968a-ef06ae1e6aba.html", "description": "Nguyen, Bachelor of Science in social studies education; Washe Ivan Osango, Bachelor of Science in speech communication; Jonathan <b>David Parker</b> ... Rachel Elaine <b>Mansfield</b>, Bachelor of Science ...", "about": [{"readLink": "https://api.cognitive.microsoft.com/api/v7/entities/08395004-52c8-7e92-072d-e7eb99cbb793", "name": "Community"}, {"readLink": "https://api.cognitive.microsoft.com/api/v7/entities/704bdc55-9de3-63f2-5d80-2ff836203d4c", "name": "Spring"}], "provider": [{"_type": "Organization", "name": "Lancaster Online", "image": {"thumbnail": {"contentUrl": "https://www.bing.com/th?id=AR_4a5bc7164e6c9f31ce74eda83891d4cd&pid=news"}}}], "datePublished": "2020-07-02T02:13:00.0000000Z"}]}